vbgptvision/__init__.py
vbgptvision/__main__.py
vbgptvision/choice_option.py
vbgptvision/functions.py
vbgptvision/main.py
vbgptvision/prompts.py
vbgptvision-0.1.2.dist-info/METADATA
vbgptvision-0.1.2.dist-info/WHEEL
vbgptvision-0.1.2.dist-info/entry_points.txt
vbgptvision-0.1.2.dist-info/RECORD
